myPackage/__init__.py
myPackage/somePython.py
python_package_example_test-0.1.dist-info/METADATA
python_package_example_test-0.1.dist-info/WHEEL
python_package_example_test-0.1.dist-info/top_level.txt
python_package_example_test-0.1.dist-info/RECORD
