Metadata-Version: 2.1
Name: python-package-example-test
Version: 0.1
Summary: An example python package
Home-page: UNKNOWN
License: UNKNOWN
Platform: UNKNOWN
